atlas_metadata_validator/__init__.py
atlas_metadata_validator/atlas_checker.py
atlas_metadata_validator/atlas_validation_config.json
atlas_metadata_validator/fetch.py
atlas_metadata_validator/file.py
atlas_metadata_validator/parser.py
atlas_metadata_validator-1.6.1.data/scripts/atlas_validation.py
atlas_metadata_validator-1.6.1.dist-info/LICENSE
atlas_metadata_validator-1.6.1.dist-info/METADATA
atlas_metadata_validator-1.6.1.dist-info/WHEEL
atlas_metadata_validator-1.6.1.dist-info/top_level.txt
atlas_metadata_validator-1.6.1.dist-info/RECORD
