Metadata-Version: 2.1
Name: atlas-metadata-validator
Version: 1.6.1
Summary: A MAGE-TAB validator for Expression Atlas and Single Cell Expression Atlas
Home-page: https://github.com/ebi-gene-expression-group/atlas-metadata-validator
Author: Anja Füllgrabe
Author-email: anjaf@ebi.ac.uk
License: Apache Software License
Platform: UNKNOWN
Classifier: Programming Language :: Python :: 3
Classifier: License :: OSI Approved :: Apache Software License
Classifier: Operating System :: OS Independent
Classifier: Topic :: Scientific/Engineering :: Bio-Informatics
Requires-Python: >=3.6
Requires-Dist: requests (>=2.20.1)
Requires-Dist: GitPython (>=3.1.7)
